anypoint/__init__.py
anypoint/access_management.py
anypoint/anypoint_exchange.py
anypoint/api_manager.py
anypoint/auth.py
anypoint/custom_logging.py
anypoint/http_client.py
anypoint/platform.py
anypoint/settings.py
anypoint_platform_api_py-0.0.1.dist-info/licenses/LICENSE
tests/__init__.py
tests/test_access_management.py
tests/test_api_manager.py
anypoint_platform_api_py-0.0.1.dist-info/METADATA
anypoint_platform_api_py-0.0.1.dist-info/WHEEL
anypoint_platform_api_py-0.0.1.dist-info/top_level.txt
anypoint_platform_api_py-0.0.1.dist-info/RECORD
