Metadata-Version: 2.4
Name: anypoint-platform-api-py
Version: 0.0.1
Summary: MuleSoft Anypoint Platform Python Library
Home-page: https://github.com/Neo-Integrations/anypoint-platform-api-py
Author: Aminul Haque
Author-email: aminul1983@Gmail.com
Classifier: Programming Language :: Python :: 3
Classifier: License :: OSI Approved :: MIT License
Classifier: Operating System :: OS Independent
License-File: LICENSE
Dynamic: author
Dynamic: author-email
Dynamic: classifier
Dynamic: description
Dynamic: description-content-type
Dynamic: home-page
Dynamic: license-file
Dynamic: summary
